pyspark_dubber/__init__.py
pyspark_dubber/docs.py
pyspark_dubber/replace_pyspark.py
pyspark_dubber/errors/__init__.py
pyspark_dubber/errors/base.py
pyspark_dubber/sql/__init__.py
pyspark_dubber/sql/dataframe.py
pyspark_dubber/sql/expr.py
pyspark_dubber/sql/grouped_data.py
pyspark_dubber/sql/input.py
pyspark_dubber/sql/output.py
pyspark_dubber/sql/row.py
pyspark_dubber/sql/session.py
pyspark_dubber/sql/types.py
pyspark_dubber/sql/functions/__init__.py
pyspark_dubber/sql/functions/_helper.py
pyspark_dubber/sql/functions/aggregate.py
pyspark_dubber/sql/functions/array.py
pyspark_dubber/sql/functions/collection.py
pyspark_dubber/sql/functions/conditional.py
pyspark_dubber/sql/functions/hash.py
pyspark_dubber/sql/functions/json.py
pyspark_dubber/sql/functions/math.py
pyspark_dubber/sql/functions/misc.py
pyspark_dubber/sql/functions/normal.py
pyspark_dubber/sql/functions/predicate.py
pyspark_dubber/sql/functions/sort.py
pyspark_dubber/sql/functions/string.py
pyspark_dubber/sql/functions/temporal.py
pyspark_dubber-0.2.4.dist-info/METADATA
pyspark_dubber-0.2.4.dist-info/WHEEL
pyspark_dubber-0.2.4.dist-info/RECORD
