Metadata-Version: 2.4
Name: pyspark-dubber
Version: 0.2.4
Summary: A compatibility layer for the pyspark API, allowing you to run pyspark code on backends such as DuckDB and Polars without porting your code.
Project-URL: documentation, https://frapa.github.io/pyspark-dubber/
Author: Marco Lotz
Author-email: Francesco Pasa <francescopasa@gmail.com>
License-Expression: LGPL-3.0-or-later
Requires-Python: >=3.10
Requires-Dist: ibis-framework[duckdb]
Requires-Dist: lark
Requires-Dist: pandas
Requires-Dist: pyarrow
Requires-Dist: pyarrow-hotfix
Requires-Dist: python-dateutil
Requires-Dist: sqlglot[rs]
Requires-Dist: tzlocal
Provides-Extra: dev
Requires-Dist: mkdocs-material; extra == 'dev'
Requires-Dist: pyspark; extra == 'dev'
Requires-Dist: pytest; extra == 'dev'
Requires-Dist: setuptools; extra == 'dev'
